ades/__init__.py
ades/base.py
ades/common.py
ades/contents.py
ades/loaders.py
ades/multipart.py
ades/serializers.py
ades/utils.py
ades/validators.py
ades/integrations/__init__.py
ades/integrations/wsgi.py
Ades-0.1.0.dev1.dist-info/METADATA
Ades-0.1.0.dev1.dist-info/WHEEL
Ades-0.1.0.dev1.dist-info/top_level.txt
Ades-0.1.0.dev1.dist-info/RECORD
