Metadata-Version: 2.1
Name: Ades
Version: 0.1.0.dev1
Summary: Validate flask inputs with openapi validators
Home-page: UNKNOWN
License: UNKNOWN
Platform: UNKNOWN
